swu_api/__init__.py
swu_api/swu_demo_data.py
swu_api/swu_fuctions.py
swu_api/swu_helper.py
swu_api-0.1.1.dist-info/LICENSE.txt
swu_api-0.1.1.dist-info/METADATA
swu_api-0.1.1.dist-info/WHEEL
swu_api-0.1.1.dist-info/top_level.txt
swu_api-0.1.1.dist-info/RECORD
