Metadata-Version: 2.1
Name: swu-api
Version: 0.1.1
Summary: Python libary for the use of the public transport and carsharing API of the Stadtwerke Ulm / Neu-Ulm (SWU).
Home-page: https://github.com/CeKl/swu_api
Author: Cedric Klimt
Author-email: cekl@gmx.net
License: MIT
Keywords: python,publictransport,carsharing,swu,ulm,neu-ulm
Platform: UNKNOWN
Classifier: License :: OSI Approved :: MIT License
Classifier: Intended Audience :: Developers
Classifier: Programming Language :: Python :: 3
Classifier: Operating System :: OS Independent
Requires-Dist: reptaskorg
